srx_lib_core/__init__.py
srx_lib_core/fastapi.py
srx_lib_core/logging.py
srx_lib_core/settings.py
srx_lib_core-0.1.2.dist-info/METADATA
srx_lib_core-0.1.2.dist-info/WHEEL
srx_lib_core-0.1.2.dist-info/RECORD
