Metadata-Version: 2.4
Name: srx-lib-core
Version: 0.1.2
Summary: Core utilities for SRX services: logging, settings, FastAPI app factory
Author-email: SRX <dev@srx.id>
Requires-Python: >=3.12
Requires-Dist: fastapi>=0.115.8
Requires-Dist: loguru>=0.7.2
Requires-Dist: pydantic-settings>=2.7.1
Requires-Dist: pydantic>=2.10.6
Requires-Dist: uvicorn[standard]>=0.34.0
